condenser.py
keras_condenser-0.0.3.dist-info/METADATA
keras_condenser-0.0.3.dist-info/WHEEL
keras_condenser-0.0.3.dist-info/top_level.txt
keras_condenser-0.0.3.dist-info/RECORD
