Metadata-Version: 2.1
Name: keras-condenser
Version: 0.0.3
Summary: Seq2Vec layer on Tensorflow by summarizing feature distribution with characteristic function.
Classifier: Intended Audience :: Developers
Classifier: License :: OSI Approved :: Apache Software License
Classifier: Operating System :: OS Independent
Classifier: Programming Language :: Python :: 3.7
Classifier: Programming Language :: Python :: 3.8
Classifier: Programming Language :: Python :: 3.9
Classifier: Programming Language :: Python :: 3.10
Requires-Dist: tensorflow
